{
    "obstacles":{
        "spawn":[
            {
                "middle_pos":{"x":11.5, "y":2.5},
                "heightWidth" : {"width": 10, "height":1}
            }
        ],
        "wall":[
            {
                "middle_pos":{"x":11.5, "y":0},
                "shape": "box",
                "heightWidth" : {"width": 11.5, "height":0.25},
                "angle":0
            },
            {
                "middle_pos":{"x":11.5, "y":31},
                "shape": "box",
                "heightWidth" : {"width": 11.5, "height":0.25},
                "angle":0
            },
            {
                "middle_pos":{"x":0, "y":15.5},
                "shape": "box",
                "heightWidth" : {"width": 0.25, "height":15.75},
                "angle":0
            },
            {
                "middle_pos":{"x":23, "y":15.5},
                "shape": "box",
                "heightWidth" : {"width": 0.25, "height":15.75},
                "angle":0
            }
        ],
        "ice":[
            {
                "middle_pos":{"x":11.5, "y":20},
                "shape": "box",
                "heightWidth" : {"width": 11.5, "height":15},
                "angle":0
            }
        ],
        "water":[
            {
                "middle_pos":{"x":11.5, "y":30},
                "shape": "box",
                "heightWidth" : {"width": 11.5, "height":2},
                "angle":0
            },
            {
                "middle_pos":{"x":8, "y":15},
                "shape": "circle",
                "heightWidth" : {"width": 2.5, "height":1.5},
                "radius": 4
            },
            {
                "middle_pos":{"x":20, "y":10},
                "shape": "circle",
                "heightWidth" : {"width": 2.5, "height":1.5},
                "radius": 3
            },
            {
                "middle_pos":{"x":21, "y":8},
                "shape": "circle",
                "heightWidth" : {"width": 2.5, "height":1.5},
                "radius": 2
            },
            {
                "middle_pos":{"x":21, "y":13},
                "shape": "circle",
                "heightWidth" : {"width": 2.5, "height":1.5},
                "radius": 2
            },
            {
                "middle_pos":{"x":18, "y":23},
                "shape": "circle",
                "heightWidth" : {"width": 2.5, "height":1.5},
                "radius": 3
            },
            {
                "middle_pos":{"x":21, "y":23},
                "shape": "circle",
                "heightWidth" : {"width": 2.5, "height":1.5},
                "radius": 2
            },
            {
                "middle_pos":{"x":8, "y":11},
                "shape": "circle",
                "heightWidth" : {"width": 2.5, "height":1.5},
                "radius": 2
            },
            {
                "middle_pos":{"x":11, "y":18},
                "shape": "circle",
                "heightWidth" : {"width": 2.5, "height":1.5},
                "radius": 2
            },
            {
                "middle_pos":{"x":7, "y":20},
                "shape": "circle",
                "heightWidth" : {"width": 2.5, "height":1.5},
                "radius": 3
            }
        ]
    },
    "hole":{
        "pos":{"x":11.5, "y":26},
        "radius":0.5
    }
}